phrases_case/__init__.py
phrases_case-0.1.1.dist-info/LICENSE
phrases_case-0.1.1.dist-info/WHEEL
phrases_case-0.1.1.dist-info/METADATA
phrases_case-0.1.1.dist-info/RECORD
