Metadata-Version: 2.1
Name: phrases-case
Version: 0.1.1
Summary: Convert phrases between different cases.
Home-page: https://github.com/NateScarlet/phrases-case
License: MIT
Author: NateScarlet
Author-email: NateScarlet@Gmail.com
Requires-Python: >=2.7, !=3.0.*, !=3.1.*, !=3.2.*, !=3.3.*
Classifier: License :: OSI Approved :: MIT License
Classifier: Programming Language :: Python :: 2
Classifier: Programming Language :: Python :: 2.7
Classifier: Programming Language :: Python :: 3
Classifier: Programming Language :: Python :: 3.4
Classifier: Programming Language :: Python :: 3.5
Classifier: Programming Language :: Python :: 3.6
Classifier: Programming Language :: Python :: 3.7
Project-URL: Repository, https://github.com/NateScarlet/phrases-case
